openmemory/__init__.py
openmemory/decay.py
openmemory/embeddings.py
openmemory/graph.py
openmemory/memory_system.py
openmemory/scoring.py
openmemory/sectors.py
openmemory/storage.py
openmemory/types.py
openmemory/mcp/__init__.py
openmemory/mcp/server.py
openmemory_python-1.0.0.dist-info/licenses/LICENSE
openmemory_python-1.0.0.dist-info/METADATA
openmemory_python-1.0.0.dist-info/WHEEL
openmemory_python-1.0.0.dist-info/entry_points.txt
openmemory_python-1.0.0.dist-info/top_level.txt
openmemory_python-1.0.0.dist-info/RECORD
