Metadata-Version: 2.4
Name: openmemory-python
Version: 1.0.0
Summary: Python implementation of OpenMemory - Long-term memory for AI systems
Home-page: https://github.com/danielsimonjr/openmemory-python
Author: Daniel Simon Jr
Author-email: 
Classifier: Development Status :: 4 - Beta
Classifier: Intended Audience :: Developers
Classifier: License :: OSI Approved :: MIT License
Classifier: Programming Language :: Python :: 3
Classifier: Programming Language :: Python :: 3.8
Classifier: Programming Language :: Python :: 3.9
Classifier: Programming Language :: Python :: 3.10
Classifier: Programming Language :: Python :: 3.11
Requires-Python: >=3.8
License-File: LICENSE
Requires-Dist: numpy>=1.24.0
Requires-Dist: sentence-transformers>=2.2.2
Requires-Dist: mcp>=0.9.0
Requires-Dist: openai>=1.0.0
Requires-Dist: python-dotenv>=1.0.0
Dynamic: author
Dynamic: classifier
Dynamic: description
Dynamic: description-content-type
Dynamic: home-page
Dynamic: license-file
Dynamic: requires-dist
Dynamic: requires-python
Dynamic: summary
